server.py
src/__init__.py
src/api/__init__.py
src/api/custom_exceptions.py
src/api/rest_client.py
src/schemas/__init__.py
src/schemas/base.py
src/schemas/branches.py
src/schemas/commits.py
src/schemas/files.py
src/schemas/groups.py
src/schemas/issues.py
src/schemas/jobs.py
src/schemas/merge_requests.py
src/schemas/repositories.py
src/schemas/search.py
src/services/__init__.py
src/services/branches.py
src/services/files.py
src/services/groups.py
src/services/issues.py
src/services/jobs.py
src/services/merge_requests.py
src/services/repositories.py
src/services/search.py
iflow_mcp_adit_999_gitlab_mcp_server-0.2.1.dist-info/METADATA
iflow_mcp_adit_999_gitlab_mcp_server-0.2.1.dist-info/WHEEL
iflow_mcp_adit_999_gitlab_mcp_server-0.2.1.dist-info/entry_points.txt
iflow_mcp_adit_999_gitlab_mcp_server-0.2.1.dist-info/licenses/LICENSE
iflow_mcp_adit_999_gitlab_mcp_server-0.2.1.dist-info/RECORD
