Metadata-Version: 2.4
Name: iflow-mcp_adit-999_gitlab-mcp-server
Version: 0.2.1
Summary: GitLab MCP (Model Context Protocol) server for interacting with GitLab API through AI Clients
Project-URL: Homepage, https://github.com/Adit-999/gitlab-mcp
Project-URL: Documentation, https://github.com/Adit-999/gitlab-mcp#readme
Author-email: Adit pal Singh <aditpalsing@gmail.com>
License: MIT License
License-File: LICENSE
Keywords: ai,gitlab,mcp,server
Classifier: Development Status :: 3 - Alpha
Classifier: Intended Audience :: Developers
Classifier: License :: OSI Approved :: MIT License
Classifier: Operating System :: OS Independent
Classifier: Programming Language :: Python :: 3.11
Classifier: Topic :: Software Development :: Libraries :: Application Frameworks
Requires-Python: >=3.11
Requires-Dist: asyncio>=3.4.3
Requires-Dist: dotenv>=0.9.9
Requires-Dist: mcp[cli]>=1.6.0
Requires-Dist: pydantic-settings>=2.8.1
Requires-Dist: pydantic>=2.11.3
Provides-Extra: dev
Requires-Dist: black>=24.2.0; extra == 'dev'
Requires-Dist: flake8>=7.0.0; extra == 'dev'
Requires-Dist: mypy>=1.8.0; extra == 'dev'
Requires-Dist: pytest-asyncio>=0.23.5; extra == 'dev'
Requires-Dist: pytest>=8.0.0; extra == 'dev'
Provides-Extra: ruff
Requires-Dist: ruff>=0.11.5; extra == 'ruff'
